{
  "category": "music-bands",
  "defaultVariant": "default",
  "variants": {
    "default": {
      "label": "Default",
      "dark": {
        "bg": {
          "base": "#080a14",
          "surface": "#0e121e",
          "elevated": "#161a28",
          "overlay": "rgba(0, 0, 0, 0.5)"
        },
        "text": {
          "primary": "#c8d0e8",
          "secondary": "#5868a0",
          "muted": "rgba(88, 104, 160, 0.6)",
          "inverse": "#080a14"
        },
        "interactive": {
          "primary": {
            "DEFAULT": "#3070d0",
            "muted": "rgba(48, 112, 208, 0.3)",
            "subtle": "rgba(48, 112, 208, 0.1)"
          },
          "secondary": {
            "DEFAULT": "#c02838",
            "muted": "rgba(192, 40, 56, 0.3)",
            "subtle": "rgba(192, 40, 56, 0.1)"
          },
          "accent": {
            "DEFAULT": "#4888e0",
            "muted": "rgba(72, 136, 224, 0.3)",
            "subtle": "rgba(72, 136, 224, 0.1)"
          }
        },
        "status": {
          "success": {
            "DEFAULT": "#48a868",
            "muted": "rgba(72, 168, 104, 0.3)",
            "subtle": "rgba(72, 168, 104, 0.1)"
          },
          "error": {
            "DEFAULT": "#d03040",
            "muted": "rgba(208, 48, 64, 0.3)",
            "subtle": "rgba(208, 48, 64, 0.1)"
          },
          "warning": {
            "DEFAULT": "#d8a030",
            "muted": "rgba(216, 160, 48, 0.3)",
            "subtle": "rgba(216, 160, 48, 0.1)"
          }
        },
        "border": {
          "default": "rgba(88, 104, 160, 0.3)",
          "subtle": "rgba(88, 104, 160, 0.15)",
          "focus": "#4888e0"
        },
        "typing": {
          "cursor": "#4888e0",
          "cursorGhost": "#c02838",
          "correct": "#c8d0e8",
          "incorrect": "#d03040",
          "upcoming": "#282e48",
          "default": "#282e48"
        }
      },
      "light": {
        "bg": {
          "base": "#eef0f8",
          "surface": "#ffffff",
          "elevated": "#e0e4f0",
          "overlay": "rgba(0, 0, 0, 0.3)"
        },
        "text": {
          "primary": "#141620",
          "secondary": "#5868a0",
          "muted": "rgba(88, 104, 160, 0.6)",
          "inverse": "#eef0f8"
        },
        "interactive": {
          "primary": {
            "DEFAULT": "#2058b0",
            "muted": "rgba(32, 88, 176, 0.2)",
            "subtle": "rgba(32, 88, 176, 0.08)"
          },
          "secondary": {
            "DEFAULT": "#a01828",
            "muted": "rgba(160, 24, 40, 0.2)",
            "subtle": "rgba(160, 24, 40, 0.08)"
          },
          "accent": {
            "DEFAULT": "#3070c8",
            "muted": "rgba(48, 112, 200, 0.2)",
            "subtle": "rgba(48, 112, 200, 0.08)"
          }
        },
        "status": {
          "success": {
            "DEFAULT": "#2a7a48",
            "muted": "rgba(42, 122, 72, 0.2)",
            "subtle": "rgba(42, 122, 72, 0.08)"
          },
          "error": {
            "DEFAULT": "#b02030",
            "muted": "rgba(176, 32, 48, 0.2)",
            "subtle": "rgba(176, 32, 48, 0.08)"
          },
          "warning": {
            "DEFAULT": "#b08020",
            "muted": "rgba(176, 128, 32, 0.2)",
            "subtle": "rgba(176, 128, 32, 0.08)"
          }
        },
        "border": {
          "default": "rgba(88, 104, 160, 0.2)",
          "subtle": "rgba(88, 104, 160, 0.1)",
          "focus": "#2058b0"
        },
        "typing": {
          "cursor": "#2058b0",
          "cursorGhost": "#3070c8",
          "correct": "#141620",
          "incorrect": "#b02030",
          "upcoming": "#8898b8",
          "default": "#8898b8"
        }
      }
    }
  }
}
