{
  "category": "music-bands",
  "defaultVariant": "default",
  "variants": {
    "default": {
      "label": "Default",
      "dark": {
        "bg": {
          "base": "#1a140a",
          "surface": "#140e06",
          "elevated": "#221a0e",
          "overlay": "rgba(0, 0, 0, 0.5)"
        },
        "text": {
          "primary": "#e8d4a8",
          "secondary": "#8a7248",
          "muted": "rgba(138, 114, 72, 0.6)",
          "inverse": "#ffffff"
        },
        "interactive": {
          "primary": {
            "DEFAULT": "#d4952a",
            "muted": "rgba(212, 149, 42, 0.3)",
            "subtle": "rgba(212, 149, 42, 0.1)"
          },
          "secondary": {
            "DEFAULT": "#c4883a",
            "muted": "rgba(196, 136, 58, 0.3)",
            "subtle": "rgba(196, 136, 58, 0.1)"
          },
          "accent": {
            "DEFAULT": "#a06830",
            "muted": "rgba(160, 104, 48, 0.3)",
            "subtle": "rgba(160, 104, 48, 0.1)"
          }
        },
        "status": {
          "success": {
            "DEFAULT": "#22c55e",
            "muted": "rgba(34, 197, 94, 0.3)",
            "subtle": "rgba(34, 197, 94, 0.1)"
          },
          "error": {
            "DEFAULT": "#dc2626",
            "muted": "rgba(220, 38, 38, 0.3)",
            "subtle": "rgba(220, 38, 38, 0.1)"
          },
          "warning": {
            "DEFAULT": "#f59e0b",
            "muted": "rgba(245, 158, 11, 0.3)",
            "subtle": "rgba(245, 158, 11, 0.1)"
          }
        },
        "border": {
          "default": "rgba(138, 114, 72, 0.3)",
          "subtle": "rgba(138, 114, 72, 0.15)",
          "focus": "#d4952a"
        },
        "typing": {
          "cursor": "#d4952a",
          "cursorGhost": "#a06830",
          "correct": "#e8d4a8",
          "incorrect": "#dc2626",
          "upcoming": "#8a7248",
          "default": "#8a7248"
        }
      },
      "light": {
        "bg": {
          "base": "#faf6ee",
          "surface": "#ffffff",
          "elevated": "#f2ece0",
          "overlay": "rgba(0, 0, 0, 0.3)"
        },
        "text": {
          "primary": "#2a2010",
          "secondary": "#9a8258",
          "muted": "rgba(154, 130, 88, 0.6)",
          "inverse": "#000000"
        },
        "interactive": {
          "primary": {
            "DEFAULT": "#b88020",
            "muted": "rgba(184, 128, 32, 0.2)",
            "subtle": "rgba(184, 128, 32, 0.08)"
          },
          "secondary": {
            "DEFAULT": "#a87830",
            "muted": "rgba(168, 120, 48, 0.2)",
            "subtle": "rgba(168, 120, 48, 0.08)"
          },
          "accent": {
            "DEFAULT": "#8a5828",
            "muted": "rgba(138, 88, 40, 0.2)",
            "subtle": "rgba(138, 88, 40, 0.08)"
          }
        },
        "status": {
          "success": {
            "DEFAULT": "#17823e",
            "muted": "rgba(23, 130, 62, 0.2)",
            "subtle": "rgba(23, 130, 62, 0.08)"
          },
          "error": {
            "DEFAULT": "#cc0000",
            "muted": "rgba(204, 0, 0, 0.2)",
            "subtle": "rgba(204, 0, 0, 0.08)"
          },
          "warning": {
            "DEFAULT": "#ab6e07",
            "muted": "rgba(171, 110, 7, 0.2)",
            "subtle": "rgba(171, 110, 7, 0.08)"
          }
        },
        "border": {
          "default": "rgba(154, 130, 88, 0.2)",
          "subtle": "rgba(154, 130, 88, 0.1)",
          "focus": "#b88020"
        },
        "typing": {
          "cursor": "#b88020",
          "cursorGhost": "#8a5828",
          "correct": "#2a2010",
          "incorrect": "#cc0000",
          "upcoming": "#9a8258",
          "default": "#9a8258"
        }
      }
    },
    "bringing-down-the-horse": {
      "label": "Bringing Down the Horse",
      "dark": {
        "bg": {
          "base": "#0e0c08",
          "surface": "#181410",
          "elevated": "#221e18",
          "overlay": "rgba(0, 0, 0, 0.6)"
        },
        "text": {
          "primary": "#e0d4b8",
          "secondary": "#80704a",
          "muted": "rgba(128, 112, 74, 0.6)",
          "inverse": "#ffffff"
        },
        "interactive": {
          "primary": {
            "DEFAULT": "#c8902a",
            "muted": "rgba(200, 144, 42, 0.3)",
            "subtle": "rgba(200, 144, 42, 0.1)"
          },
          "secondary": {
            "DEFAULT": "#9a7030",
            "muted": "rgba(154, 112, 48, 0.3)",
            "subtle": "rgba(154, 112, 48, 0.1)"
          },
          "accent": {
            "DEFAULT": "#d8a850",
            "muted": "rgba(216, 168, 80, 0.3)",
            "subtle": "rgba(216, 168, 80, 0.1)"
          }
        },
        "status": {
          "success": {
            "DEFAULT": "#22c55e",
            "muted": "rgba(34, 197, 94, 0.3)",
            "subtle": "rgba(34, 197, 94, 0.1)"
          },
          "error": {
            "DEFAULT": "#ef4444",
            "muted": "rgba(239, 68, 68, 0.3)",
            "subtle": "rgba(239, 68, 68, 0.1)"
          },
          "warning": {
            "DEFAULT": "#f59e0b",
            "muted": "rgba(245, 158, 11, 0.3)",
            "subtle": "rgba(245, 158, 11, 0.1)"
          }
        },
        "border": {
          "default": "rgba(128, 112, 74, 0.3)",
          "subtle": "rgba(128, 112, 74, 0.15)",
          "focus": "#c8902a"
        },
        "typing": {
          "cursor": "#c8902a",
          "cursorGhost": "#d8a850",
          "correct": "#e0d4b8",
          "incorrect": "#ef4444",
          "upcoming": "#80704a",
          "default": "#80704a"
        }
      },
      "light": {
        "bg": {
          "base": "#faf6ec",
          "surface": "#ffffff",
          "elevated": "#f2ecdc",
          "overlay": "rgba(0, 0, 0, 0.3)"
        },
        "text": {
          "primary": "#201808",
          "secondary": "#908060",
          "muted": "rgba(144, 128, 96, 0.6)",
          "inverse": "#000000"
        },
        "interactive": {
          "primary": {
            "DEFAULT": "#aa7820",
            "muted": "rgba(170, 120, 32, 0.2)",
            "subtle": "rgba(170, 120, 32, 0.08)"
          },
          "secondary": {
            "DEFAULT": "#7e5a20",
            "muted": "rgba(126, 90, 32, 0.2)",
            "subtle": "rgba(126, 90, 32, 0.08)"
          },
          "accent": {
            "DEFAULT": "#b89038",
            "muted": "rgba(184, 144, 56, 0.2)",
            "subtle": "rgba(184, 144, 56, 0.08)"
          }
        },
        "status": {
          "success": {
            "DEFAULT": "#17823e",
            "muted": "rgba(23, 130, 62, 0.2)",
            "subtle": "rgba(23, 130, 62, 0.08)"
          },
          "error": {
            "DEFAULT": "#e03030",
            "muted": "rgba(224, 48, 48, 0.2)",
            "subtle": "rgba(224, 48, 48, 0.08)"
          },
          "warning": {
            "DEFAULT": "#ab6e07",
            "muted": "rgba(171, 110, 7, 0.2)",
            "subtle": "rgba(171, 110, 7, 0.08)"
          }
        },
        "border": {
          "default": "rgba(144, 128, 96, 0.2)",
          "subtle": "rgba(144, 128, 96, 0.1)",
          "focus": "#aa7820"
        },
        "typing": {
          "cursor": "#aa7820",
          "cursorGhost": "#b89038",
          "correct": "#201808",
          "incorrect": "#e03030",
          "upcoming": "#908060",
          "default": "#908060"
        }
      }
    },
    "breach": {
      "label": "Breach",
      "dark": {
        "bg": {
          "base": "#080a0e",
          "surface": "#101420",
          "elevated": "#181e2e",
          "overlay": "rgba(0, 0, 0, 0.6)"
        },
        "text": {
          "primary": "#c8d4e8",
          "secondary": "#506080",
          "muted": "rgba(80, 96, 128, 0.6)",
          "inverse": "#ffffff"
        },
        "interactive": {
          "primary": {
            "DEFAULT": "#4870c0",
            "muted": "rgba(72, 112, 192, 0.3)",
            "subtle": "rgba(72, 112, 192, 0.1)"
          },
          "secondary": {
            "DEFAULT": "#c8902a",
            "muted": "rgba(200, 144, 42, 0.3)",
            "subtle": "rgba(200, 144, 42, 0.1)"
          },
          "accent": {
            "DEFAULT": "#6890d8",
            "muted": "rgba(104, 144, 216, 0.3)",
            "subtle": "rgba(104, 144, 216, 0.1)"
          }
        },
        "status": {
          "success": {
            "DEFAULT": "#22c55e",
            "muted": "rgba(34, 197, 94, 0.3)",
            "subtle": "rgba(34, 197, 94, 0.1)"
          },
          "error": {
            "DEFAULT": "#ef4444",
            "muted": "rgba(239, 68, 68, 0.3)",
            "subtle": "rgba(239, 68, 68, 0.1)"
          },
          "warning": {
            "DEFAULT": "#f59e0b",
            "muted": "rgba(245, 158, 11, 0.3)",
            "subtle": "rgba(245, 158, 11, 0.1)"
          }
        },
        "border": {
          "default": "rgba(80, 96, 128, 0.3)",
          "subtle": "rgba(80, 96, 128, 0.15)",
          "focus": "#4870c0"
        },
        "typing": {
          "cursor": "#4870c0",
          "cursorGhost": "#6890d8",
          "correct": "#c8d4e8",
          "incorrect": "#ef4444",
          "upcoming": "#506080",
          "default": "#506080"
        }
      },
      "light": {
        "bg": {
          "base": "#f0f4fc",
          "surface": "#ffffff",
          "elevated": "#e2ecf8",
          "overlay": "rgba(0, 0, 0, 0.3)"
        },
        "text": {
          "primary": "#101828",
          "secondary": "#607090",
          "muted": "rgba(96, 112, 144, 0.6)",
          "inverse": "#000000"
        },
        "interactive": {
          "primary": {
            "DEFAULT": "#3458a8",
            "muted": "rgba(52, 88, 168, 0.2)",
            "subtle": "rgba(52, 88, 168, 0.08)"
          },
          "secondary": {
            "DEFAULT": "#aa7820",
            "muted": "rgba(170, 120, 32, 0.2)",
            "subtle": "rgba(170, 120, 32, 0.08)"
          },
          "accent": {
            "DEFAULT": "#4870c0",
            "muted": "rgba(72, 112, 192, 0.2)",
            "subtle": "rgba(72, 112, 192, 0.08)"
          }
        },
        "status": {
          "success": {
            "DEFAULT": "#17823e",
            "muted": "rgba(23, 130, 62, 0.2)",
            "subtle": "rgba(23, 130, 62, 0.08)"
          },
          "error": {
            "DEFAULT": "#e03030",
            "muted": "rgba(224, 48, 48, 0.2)",
            "subtle": "rgba(224, 48, 48, 0.08)"
          },
          "warning": {
            "DEFAULT": "#ab6e07",
            "muted": "rgba(171, 110, 7, 0.2)",
            "subtle": "rgba(171, 110, 7, 0.08)"
          }
        },
        "border": {
          "default": "rgba(96, 112, 144, 0.2)",
          "subtle": "rgba(96, 112, 144, 0.1)",
          "focus": "#3458a8"
        },
        "typing": {
          "cursor": "#3458a8",
          "cursorGhost": "#4870c0",
          "correct": "#101828",
          "incorrect": "#e03030",
          "upcoming": "#607090",
          "default": "#607090"
        }
      }
    },
    "rebel-sweetheart": {
      "label": "Rebel Sweetheart",
      "dark": {
        "bg": {
          "base": "#100808",
          "surface": "#1a1010",
          "elevated": "#241818",
          "overlay": "rgba(0, 0, 0, 0.6)"
        },
        "text": {
          "primary": "#e0c8c0",
          "secondary": "#806050",
          "muted": "rgba(128, 96, 80, 0.6)",
          "inverse": "#ffffff"
        },
        "interactive": {
          "primary": {
            "DEFAULT": "#c04030",
            "muted": "rgba(192, 64, 48, 0.3)",
            "subtle": "rgba(192, 64, 48, 0.1)"
          },
          "secondary": {
            "DEFAULT": "#d4902a",
            "muted": "rgba(212, 144, 42, 0.3)",
            "subtle": "rgba(212, 144, 42, 0.1)"
          },
          "accent": {
            "DEFAULT": "#d86050",
            "muted": "rgba(216, 96, 80, 0.3)",
            "subtle": "rgba(216, 96, 80, 0.1)"
          }
        },
        "status": {
          "success": {
            "DEFAULT": "#22c55e",
            "muted": "rgba(34, 197, 94, 0.3)",
            "subtle": "rgba(34, 197, 94, 0.1)"
          },
          "error": {
            "DEFAULT": "#ef4444",
            "muted": "rgba(239, 68, 68, 0.3)",
            "subtle": "rgba(239, 68, 68, 0.1)"
          },
          "warning": {
            "DEFAULT": "#f59e0b",
            "muted": "rgba(245, 158, 11, 0.3)",
            "subtle": "rgba(245, 158, 11, 0.1)"
          }
        },
        "border": {
          "default": "rgba(128, 96, 80, 0.3)",
          "subtle": "rgba(128, 96, 80, 0.15)",
          "focus": "#c04030"
        },
        "typing": {
          "cursor": "#c04030",
          "cursorGhost": "#d86050",
          "correct": "#e0c8c0",
          "incorrect": "#ef4444",
          "upcoming": "#806050",
          "default": "#806050"
        }
      },
      "light": {
        "bg": {
          "base": "#faf4f2",
          "surface": "#ffffff",
          "elevated": "#f2e8e4",
          "overlay": "rgba(0, 0, 0, 0.3)"
        },
        "text": {
          "primary": "#201410",
          "secondary": "#907060",
          "muted": "rgba(144, 112, 96, 0.6)",
          "inverse": "#000000"
        },
        "interactive": {
          "primary": {
            "DEFAULT": "#a03020",
            "muted": "rgba(160, 48, 32, 0.2)",
            "subtle": "rgba(160, 48, 32, 0.08)"
          },
          "secondary": {
            "DEFAULT": "#b07820",
            "muted": "rgba(176, 120, 32, 0.2)",
            "subtle": "rgba(176, 120, 32, 0.08)"
          },
          "accent": {
            "DEFAULT": "#b84838",
            "muted": "rgba(184, 72, 56, 0.2)",
            "subtle": "rgba(184, 72, 56, 0.08)"
          }
        },
        "status": {
          "success": {
            "DEFAULT": "#17823e",
            "muted": "rgba(23, 130, 62, 0.2)",
            "subtle": "rgba(23, 130, 62, 0.08)"
          },
          "error": {
            "DEFAULT": "#e03030",
            "muted": "rgba(224, 48, 48, 0.2)",
            "subtle": "rgba(224, 48, 48, 0.08)"
          },
          "warning": {
            "DEFAULT": "#ab6e07",
            "muted": "rgba(171, 110, 7, 0.2)",
            "subtle": "rgba(171, 110, 7, 0.08)"
          }
        },
        "border": {
          "default": "rgba(144, 112, 96, 0.2)",
          "subtle": "rgba(144, 112, 96, 0.1)",
          "focus": "#a03020"
        },
        "typing": {
          "cursor": "#a03020",
          "cursorGhost": "#b84838",
          "correct": "#201410",
          "incorrect": "#e03030",
          "upcoming": "#907060",
          "default": "#907060"
        }
      }
    }
  }
}
